starri/__init__.py
starri/menu.py
starri-1.7.3.dist-info/METADATA
starri-1.7.3.dist-info/WHEEL
starri-1.7.3.dist-info/top_level.txt
starri-1.7.3.dist-info/RECORD
