Metadata-Version: 2.4
Name: starri
Version: 1.7.3
Summary: A terminal-based menu system using blessed.
Home-page: https://github.com/lioen-dev/starri
Author: Rowan Barker
Author-email: barker.rowan@sugarsalem.com
Requires-Dist: blessed>=1.20.0
Requires-Dist: py-gradify
Dynamic: author
Dynamic: author-email
Dynamic: description
Dynamic: description-content-type
Dynamic: home-page
Dynamic: requires-dist
Dynamic: summary
